ezfsm/DataArea.py
ezfsm/StateMachine.py
ezfsm/StateNode.py
ezfsm/StateSet.py
ezfsm/TimingSeriesFunction.py
ezfsm/TransFunction.py
ezfsm/__init__.py
ezfsm/unit_test.py
ezfsm/vessel.py
ezfsm-0.2.1.2.dist-info/METADATA
ezfsm-0.2.1.2.dist-info/WHEEL
ezfsm-0.2.1.2.dist-info/top_level.txt
ezfsm-0.2.1.2.dist-info/RECORD
