Metadata-Version: 2.1
Name: ezfsm
Version: 0.2.1.2
Summary: > Easy and micro fsm could used in python3.x and micropython.
Home-page: https://gitee.com/eagle-s_baby/fsm/blob/master/README.md
Author: Eagle'sBaby
Author-email: 2229066748@qq.com
Maintainer: Eagle'sBaby
Maintainer-email: 2229066748@qq.com
License: Apache Licence 2.0
Keywords: fsm,micropython
Platform: all
Classifier: Programming Language :: Python
Classifier: Programming Language :: Python :: 3
Requires-Python: >=3
